python_wml-3.1.7.dist-info/licenses/LICENSE
wml/__init__.py
wml/basic_img_utils.py
wml/basic_utils.py
wml/env_utils.py
wml/img_patch.py
wml/img_utils.py
wml/mci.py
wml/threadtoolkit.py
wml/walgorithm.py
wml/wcollections.py
wml/wfilesystem.py
wml/wml_utils.py
wml/basic_data_def/__init__.py
wml/basic_data_def/detection_data_def.py
wml/basic_data_def/io_data_def.py
wml/datasets_tools/__init__.py
wml/datasets_tools/add_folder_for_images.py
wml/datasets_tools/annotation_patch.py
wml/datasets_tools/build_gif.py
wml/datasets_tools/build_images_labels.py
wml/datasets_tools/build_npframes.py
wml/datasets_tools/build_rawframes.py
wml/datasets_tools/build_videos.py
wml/datasets_tools/check_duplicate_files.py
wml/datasets_tools/check_split_dataset.py
wml/datasets_tools/classification_statistics.py
wml/datasets_tools/cmp_datasets.py
wml/datasets_tools/cmp_image_folder.py
wml/datasets_tools/cmp_kps_datasets.py
wml/datasets_tools/concat_video_files.py
wml/datasets_tools/copy_annotation_for_img.py
wml/datasets_tools/copy_img_for_annotation.py
wml/datasets_tools/cut_dataset.py
wml/datasets_tools/dir_info.py
wml/datasets_tools/draw_text_on_imgs.py
wml/datasets_tools/find_imgs.py
wml/datasets_tools/find_same_name_files.py
wml/datasets_tools/frames2npframes.py
wml/datasets_tools/get_bbox_sizes_and_ratios.py
wml/datasets_tools/img_mean_std.py
wml/datasets_tools/img_statistics_tools.py
wml/datasets_tools/make_ann_for_imgs.py
wml/datasets_tools/make_statistics_file.py
wml/datasets_tools/mckps_statistics_tools.py
wml/datasets_tools/misc_tools.py
wml/datasets_tools/move_by_file_names.py
wml/datasets_tools/record_videos.py
wml/datasets_tools/remove_different_files.py
wml/datasets_tools/remove_duplicate_files.py
wml/datasets_tools/remove_files_by_label.py
wml/datasets_tools/remove_imgs_or_annotations.py
wml/datasets_tools/remove_labelme_imagedata.py
wml/datasets_tools/remove_pacal_voc_label.py
wml/datasets_tools/remove_same_name_files.py
wml/datasets_tools/rename2labels.py
wml/datasets_tools/rename_subdir_name.py
python_wml-3.1.7.dist-info/METADATA
python_wml-3.1.7.dist-info/WHEEL
python_wml-3.1.7.dist-info/top_level.txt
python_wml-3.1.7.dist-info/RECORD
