Metadata-Version: 2.4
Name: python-wml
Version: 3.1.7
Summary: Deep Learning toolkit
Home-page: https://github.com/vghost2008/wml
Author: vghost2008
Author-email: bluetornado@zju.edu.cn
Classifier: Programming Language :: Python :: 3
Classifier: License :: OSI Approved :: MIT License
Classifier: Operating System :: OS Independent
Requires-Python: >=3.6
License-File: LICENSE
Requires-Dist: opencv-python>=4.5.3.56
Requires-Dist: pycocotools>=2.0.7
Requires-Dist: gast>=0.2.2
Requires-Dist: yacs>=0.1.8
Requires-Dist: scikit-learn
Requires-Dist: pandas>=0.23.0
Requires-Dist: PyTurboJPEG
Requires-Dist: einops
Requires-Dist: easydict
Requires-Dist: colorama
Requires-Dist: imageio
Dynamic: author
Dynamic: author-email
Dynamic: classifier
Dynamic: description
Dynamic: description-content-type
Dynamic: home-page
Dynamic: license-file
Dynamic: requires-dist
Dynamic: requires-python
Dynamic: summary
